sqlinspector2/__init__.py
sqlinspector2/apps.py
sqlinspector2/middleware.py
sqlinspector2-1.0.6.dist-info/METADATA
sqlinspector2-1.0.6.dist-info/RECORD
sqlinspector2-1.0.6.dist-info/WHEEL
sqlinspector2-1.0.6.dist-info/top_level.txt
