Metadata-Version: 2.1
Name: sqlinspector2
Version: 1.0.6
Summary: Middleware that allow check the times applied and the SQL amount used on any request and response process on django
Home-page: https://franklintiel.github.io/sqlinspector2/
Author: Franklin Sarmiento
Author-email: franklinitiel@gmail.com
License: MIT
Project-URL: Documentation, https://franklintiel.github.io/sqlinspector2/
Project-URL: Source, https://github.com/franklintiel/sqlinspector2
Project-URL: Tracker, https://github.com/franklintiel/sqlinspector2/issues
Keywords: sql inspector sqlinspector django2
Platform: UNKNOWN
Classifier: Development Status :: 5 - Production/Stable
Classifier: License :: OSI Approved :: MIT License
Classifier: Programming Language :: Python :: 3.5
Requires-Python: >=3.*
Requires-Dist: Django
